{"ParsedResults":[{"TextOverlay":{"Lines":[{"LineText":"héres, herédis (m.). heir","Words":[{"WordText":"héres,","Left":238.0,"Top":1.0,"Height":18.0,"Width":47.0},{"WordText":"herédis","Left":289.0,"Top":3.0,"Height":16.0,"Width":58.0},{"WordText":"(m.).","Left":352.0,"Top":4.0,"Height":18.0,"Width":36.0},{"WordText":"heir","Left":393.0,"Top":5.0,"Height":15.0,"Width":30.0}],"MaxHeight":18.0,"MinTop":1.0},{"LineText":"hérös, heroidis hero","Words":[{"WordText":"hérös,","Left":238.0,"Top":28.0,"Height":18.0,"Width":49.0},{"WordText":"heroidis","Left":291.0,"Top":30.0,"Height":16.0,"Width":65.0},{"WordText":"hero","Left":401.0,"Top":32.0,"Height":15.0,"Width":33.0}],"MaxHeight":18.0,"MinTop":28.0},{"LineText":"hesternus, -a, -um. of or belonging to yesterday,","Words":[{"WordText":"hesternus,","Left":238.0,"Top":56.0,"Height":18.0,"Width":82.0},{"WordText":"-a,","Left":325.0,"Top":63.0,"Height":12.0,"Width":19.0},{"WordText":"-um.","Left":349.0,"Top":63.0,"Height":10.0,"Width":36.0},{"WordText":"of","Left":390.0,"Top":59.0,"Height":15.0,"Width":17.0},{"WordText":"or","Left":409.0,"Top":64.0,"Height":10.0,"Width":17.0},{"WordText":"belonging","Left":429.0,"Top":59.0,"Height":19.0,"Width":76.0},{"WordText":"to","Left":509.0,"Top":61.0,"Height":12.0,"Width":14.0},{"WordText":"yesterday,","Left":528.0,"Top":57.0,"Height":21.0,"Width":74.0}],"MaxHeight":21.0,"MinTop":56.0},{"LineText":"yesterday's","Words":[{"WordText":"yesterday's","Left":276.0,"Top":80.0,"Height":20.0,"Width":83.0}],"MaxHeight":20.0,"MinTop":80.0},{"LineText":"heu (interj.). alas! Oh no!","Words":[{"WordText":"heu","Left":238.0,"Top":106.0,"Height":14.0,"Width":29.0},{"WordText":"(interj.).","Left":272.0,"Top":106.0,"Height":20.0,"Width":63.0},{"WordText":"alas!","Left":341.0,"Top":108.0,"Height":15.0,"Width":33.0},{"WordText":"Oh","Left":379.0,"Top":108.0,"Height":15.0,"Width":19.0},{"WordText":"no!","Left":403.0,"Top":109.0,"Height":14.0,"Width":23.0}],"MaxHeight":20.0,"MinTop":106.0},{"LineText":"hic, haec, hoc. this","Words":[{"WordText":"hic,","Left":238.0,"Top":133.0,"Height":17.0,"Width":29.0},{"WordText":"haec,","Left":272.0,"Top":133.0,"Height":17.0,"Width":40.0},{"WordText":"hoc.","Left":316.0,"Top":134.0,"Height":15.0,"Width":33.0},{"WordText":"this","Left":354.0,"Top":135.0,"Height":15.0,"Width":28.0}],"MaxHeight":17.0,"MinTop":133.0},{"LineText":"hinc (adv.). from here, next; [with illincl on this side","Words":[{"WordText":"hinc","Left":238.0,"Top":160.0,"Height":15.0,"Width":35.0},{"WordText":"(adv.).","Left":278.0,"Top":161.0,"Height":17.0,"Width":46.0},{"WordText":"from","Left":330.0,"Top":161.0,"Height":15.0,"Width":37.0},{"WordText":"here,","Left":372.0,"Top":162.0,"Height":16.0,"Width":36.0},{"WordText":"next;","Left":413.0,"Top":165.0,"Height":14.0,"Width":36.0},{"WordText":"[with","Left":456.0,"Top":161.0,"Height":18.0,"Width":36.0},{"WordText":"illincl","Left":497.0,"Top":161.0,"Height":18.0,"Width":43.0},{"WordText":"on","Left":546.0,"Top":166.0,"Height":10.0,"Width":19.0},{"WordText":"this","Left":569.0,"Top":161.0,"Height":15.0,"Width":29.0},{"WordText":"side","Left":602.0,"Top":161.0,"Height":15.0,"Width":30.0}],"MaxHeight":18.0,"MinTop":160.0},{"LineText":"hisco, hiscere, -, to open, to yawn","Words":[{"WordText":"hisco,","Left":238.0,"Top":187.0,"Height":17.0,"Width":46.0},{"WordText":"hiscere,","Left":288.0,"Top":188.0,"Height":17.0,"Width":61.0},{"WordText":"-,","Left":353.0,"Top":196.0,"Height":9.0,"Width":11.0},{"WordText":"to","Left":383.0,"Top":191.0,"Height":12.0,"Width":15.0},{"WordText":"open,","Left":402.0,"Top":193.0,"Height":15.0,"Width":42.0},{"WordText":"to","Left":449.0,"Top":191.0,"Height":12.0,"Width":14.0},{"WordText":"yawn","Left":467.0,"Top":193.0,"Height":14.0,"Width":40.0}],"MaxHeight":17.0,"MinTop":187.0},{"LineText":"hodié (adv.). today","Words":[{"WordText":"hodié","Left":238.0,"Top":214.0,"Height":15.0,"Width":45.0},{"WordText":"(adv.).","Left":287.0,"Top":215.0,"Height":17.0,"Width":47.0},{"WordText":"today","Left":339.0,"Top":215.0,"Height":19.0,"Width":42.0}],"MaxHeight":19.0,"MinTop":214.0},{"LineText":"holus, holeris vegetable","Words":[{"WordText":"holus,","Left":238.0,"Top":241.0,"Height":16.0,"Width":48.0},{"WordText":"holeris","Left":290.0,"Top":241.0,"Height":16.0,"Width":53.0},{"WordText":"vegetable","Left":383.0,"Top":242.0,"Height":19.0,"Width":69.0}],"MaxHeight":19.0,"MinTop":241.0},{"LineText":"honestus, -a, -urn. honorable, forthright, upstanding","Words":[{"WordText":"honestus,","Left":238.0,"Top":267.0,"Height":18.0,"Width":75.0},{"WordText":"-a,","Left":317.0,"Top":273.0,"Height":12.0,"Width":20.0},{"WordText":"-urn.","Left":342.0,"Top":273.0,"Height":10.0,"Width":36.0},{"WordText":"honorable,","Left":383.0,"Top":269.0,"Height":17.0,"Width":80.0},{"WordText":"forthright,","Left":467.0,"Top":269.0,"Height":20.0,"Width":80.0},{"WordText":"upstanding","Left":552.0,"Top":270.0,"Height":19.0,"Width":86.0}],"MaxHeight":20.0,"MinTop":267.0},{"LineText":"honor, honoris honor, glory, distinction, beauty","Words":[{"WordText":"honor,","Left":238.0,"Top":294.0,"Height":17.0,"Width":51.0},{"WordText":"honoris","Left":293.0,"Top":295.0,"Height":15.0,"Width":60.0},{"WordText":"honor,","Left":398.0,"Top":296.0,"Height":17.0,"Width":49.0},{"WordText":"glory,","Left":452.0,"Top":297.0,"Height":19.0,"Width":42.0},{"WordText":"distinction,","Left":499.0,"Top":297.0,"Height":17.0,"Width":86.0},{"WordText":"beauty","Left":589.0,"Top":298.0,"Height":19.0,"Width":52.0}],"MaxHeight":19.0,"MinTop":294.0},{"LineText":"höra, -ae. hour, time","Words":[{"WordText":"höra,","Left":238.0,"Top":321.0,"Height":17.0,"Width":41.0},{"WordText":"-ae.","Left":284.0,"Top":326.0,"Height":11.0,"Width":27.0},{"WordText":"hour,","Left":315.0,"Top":322.0,"Height":17.0,"Width":41.0},{"WordText":"time","Left":361.0,"Top":324.0,"Height":13.0,"Width":34.0}],"MaxHeight":17.0,"MinTop":321.0},{"LineText":"horridus, -a, -urn. horrid, horrible, awful, terrible","Words":[{"WordText":"horridus,","Left":238.0,"Top":348.0,"Height":17.0,"Width":72.0},{"WordText":"-a,","Left":315.0,"Top":354.0,"Height":12.0,"Width":20.0},{"WordText":"-urn.","Left":340.0,"Top":354.0,"Height":10.0,"Width":36.0},{"WordText":"horrid,","Left":381.0,"Top":350.0,"Height":16.0,"Width":53.0},{"WordText":"horrible,","Left":438.0,"Top":350.0,"Height":17.0,"Width":65.0},{"WordText":"awful,","Left":508.0,"Top":351.0,"Height":17.0,"Width":46.0},{"WordText":"terrible","Left":559.0,"Top":352.0,"Height":15.0,"Width":55.0}],"MaxHeight":17.0,"MinTop":348.0},{"LineText":"hortor, hortäri, hortätus. to encourage","Words":[{"WordText":"hortor,","Left":238.0,"Top":375.0,"Height":17.0,"Width":54.0},{"WordText":"hortäri,","Left":297.0,"Top":376.0,"Height":17.0,"Width":61.0},{"WordText":"hortätus.","Left":362.0,"Top":376.0,"Height":16.0,"Width":70.0},{"WordText":"to","Left":437.0,"Top":380.0,"Height":12.0,"Width":15.0},{"WordText":"encourage","Left":457.0,"Top":382.0,"Height":15.0,"Width":78.0}],"MaxHeight":17.0,"MinTop":375.0},{"LineText":"hortus, -i. garden","Words":[{"WordText":"hortus,","Left":238.0,"Top":402.0,"Height":17.0,"Width":56.0},{"WordText":"-i.","Left":299.0,"Top":404.0,"Height":13.0,"Width":16.0},{"WordText":"garden","Left":319.0,"Top":403.0,"Height":19.0,"Width":53.0}],"MaxHeight":19.0,"MinTop":402.0},{"LineText":"hospes, hospitis (m.). guest, host, friend, visitor","Words":[{"WordText":"hospes,","Left":238.0,"Top":429.0,"Height":18.0,"Width":57.0},{"WordText":"hospitis","Left":300.0,"Top":429.0,"Height":19.0,"Width":61.0},{"WordText":"(m.).","Left":366.0,"Top":430.0,"Height":17.0,"Width":35.0},{"WordText":"guest,","Left":406.0,"Top":434.0,"Height":15.0,"Width":44.0},{"WordText":"host,","Left":455.0,"Top":431.0,"Height":16.0,"Width":37.0},{"WordText":"friend,","Left":496.0,"Top":431.0,"Height":17.0,"Width":51.0},{"WordText":"visitor","Left":551.0,"Top":433.0,"Height":14.0,"Width":48.0}],"MaxHeight":19.0,"MinTop":429.0},{"LineText":"hostis, -is enemy","Words":[{"WordText":"hostis,","Left":238.0,"Top":456.0,"Height":16.0,"Width":50.0},{"WordText":"-is","Left":293.0,"Top":457.0,"Height":14.0,"Width":19.0},{"WordText":"enemy","Left":357.0,"Top":461.0,"Height":15.0,"Width":51.0}],"MaxHeight":16.0,"MinTop":456.0},{"LineText":"hüc (adv.). to this place, here","Words":[{"WordText":"hüc","Left":237.0,"Top":482.0,"Height":15.0,"Width":29.0},{"WordText":"(adv.).","Left":270.0,"Top":482.0,"Height":18.0,"Width":47.0},{"WordText":"to","Left":322.0,"Top":485.0,"Height":12.0,"Width":15.0},{"WordText":"this","Left":341.0,"Top":483.0,"Height":15.0,"Width":29.0},{"WordText":"place,","Left":374.0,"Top":483.0,"Height":19.0,"Width":44.0},{"WordText":"here","Left":422.0,"Top":484.0,"Height":15.0,"Width":33.0}],"MaxHeight":19.0,"MinTop":482.0},{"LineText":"humilis, -e. humble, lowly","Words":[{"WordText":"humilis,","Left":237.0,"Top":509.0,"Height":17.0,"Width":66.0},{"WordText":"-e.","Left":308.0,"Top":514.0,"Height":10.0,"Width":18.0},{"WordText":"humble,","Left":331.0,"Top":509.0,"Height":17.0,"Width":62.0},{"WordText":"lowly","Left":397.0,"Top":510.0,"Height":19.0,"Width":41.0}],"MaxHeight":19.0,"MinTop":509.0},{"LineText":"humus, -i (f.). earth, dirt, soil","Words":[{"WordText":"humus,","Left":237.0,"Top":536.0,"Height":16.0,"Width":59.0},{"WordText":"-i","Left":301.0,"Top":538.0,"Height":12.0,"Width":11.0},{"WordText":"(f.).","Left":317.0,"Top":536.0,"Height":17.0,"Width":25.0},{"WordText":"earth,","Left":348.0,"Top":537.0,"Height":16.0,"Width":44.0},{"WordText":"dirt,","Left":397.0,"Top":537.0,"Height":16.0,"Width":33.0},{"WordText":"soil","Left":435.0,"Top":537.0,"Height":15.0,"Width":26.0}],"MaxHeight":17.0,"MinTop":536.0},{"LineText":"Hymén, Hymenis (name: god of marriage]","Words":[{"WordText":"Hymén,","Left":238.0,"Top":563.0,"Height":18.0,"Width":62.0},{"WordText":"Hymenis","Left":305.0,"Top":563.0,"Height":19.0,"Width":70.0},{"WordText":"(name:","Left":422.0,"Top":563.0,"Height":18.0,"Width":50.0},{"WordText":"god","Left":475.0,"Top":564.0,"Height":19.0,"Width":28.0},{"WordText":"of","Left":507.0,"Top":564.0,"Height":19.0,"Width":17.0},{"WordText":"marriage]","Left":525.0,"Top":565.0,"Height":19.0,"Width":72.0}],"MaxHeight":19.0,"MinTop":563.0},{"LineText":"Hymettius, -a, -urn. Hymettian; of or belonging to Mt.","Words":[{"WordText":"Hymettius,","Left":238.0,"Top":590.0,"Height":18.0,"Width":87.0},{"WordText":"-a,","Left":331.0,"Top":594.0,"Height":12.0,"Width":19.0},{"WordText":"-urn.","Left":355.0,"Top":594.0,"Height":10.0,"Width":36.0},{"WordText":"Hymettian;","Left":396.0,"Top":591.0,"Height":18.0,"Width":87.0},{"WordText":"of","Left":488.0,"Top":591.0,"Height":14.0,"Width":16.0},{"WordText":"or","Left":507.0,"Top":596.0,"Height":9.0,"Width":16.0},{"WordText":"belonging","Left":527.0,"Top":591.0,"Height":20.0,"Width":74.0},{"WordText":"to","Left":606.0,"Top":595.0,"Height":11.0,"Width":14.0},{"WordText":"Mt.","Left":625.0,"Top":593.0,"Height":14.0,"Width":25.0}],"MaxHeight":20.0,"MinTop":590.0},{"LineText":"Hymettius [a mountain near Athens noted for its","Words":[{"WordText":"Hymettius","Left":275.0,"Top":612.0,"Height":18.0,"Width":81.0},{"WordText":"[a","Left":362.0,"Top":612.0,"Height":17.0,"Width":13.0},{"WordText":"mountain","Left":381.0,"Top":614.0,"Height":13.0,"Width":72.0},{"WordText":"near","Left":459.0,"Top":617.0,"Height":10.0,"Width":33.0},{"WordText":"Athens","Left":495.0,"Top":613.0,"Height":15.0,"Width":52.0},{"WordText":"noted","Left":552.0,"Top":614.0,"Height":14.0,"Width":41.0},{"WordText":"for","Left":593.0,"Top":614.0,"Height":19.0,"Width":25.0},{"WordText":"its","Left":622.0,"Top":615.0,"Height":14.0,"Width":17.0}],"MaxHeight":19.0,"MinTop":612.0},{"LineText":"honey]","Words":[{"WordText":"honey]","Left":275.0,"Top":633.0,"Height":19.0,"Width":49.0}],"MaxHeight":19.0,"MinTop":633.0},{"LineText":"iaceö, iacére, iacui, iaciturus. to lie down, to lie still, to lie","Words":[{"WordText":"iaceö,","Left":238.0,"Top":687.0,"Height":16.0,"Width":45.0},{"WordText":"iacére,","Left":288.0,"Top":687.0,"Height":16.0,"Width":50.0},{"WordText":"iacui,","Left":343.0,"Top":688.0,"Height":15.0,"Width":41.0},{"WordText":"iaciturus.","Left":389.0,"Top":688.0,"Height":14.0,"Width":74.0},{"WordText":"to","Left":468.0,"Top":690.0,"Height":12.0,"Width":14.0},{"WordText":"lie","Left":487.0,"Top":688.0,"Height":14.0,"Width":17.0},{"WordText":"down,","Left":509.0,"Top":688.0,"Height":16.0,"Width":46.0},{"WordText":"to","Left":560.0,"Top":691.0,"Height":12.0,"Width":14.0},{"WordText":"lie","Left":578.0,"Top":689.0,"Height":14.0,"Width":18.0},{"WordText":"still,","Left":600.0,"Top":689.0,"Height":17.0,"Width":32.0},{"WordText":"to","Left":637.0,"Top":693.0,"Height":11.0,"Width":15.0},{"WordText":"lie","Left":656.0,"Top":689.0,"Height":15.0,"Width":18.0}],"MaxHeight":17.0,"MinTop":687.0},{"LineText":"motionless","Words":[{"WordText":"motionless","Left":276.0,"Top":709.0,"Height":15.0,"Width":82.0}],"MaxHeight":15.0,"MinTop":709.0},{"LineText":"iam (adv.). now, already","Words":[{"WordText":"iam","Left":238.0,"Top":736.0,"Height":13.0,"Width":30.0},{"WordText":"(adv.).","Left":273.0,"Top":735.0,"Height":17.0,"Width":46.0},{"WordText":"now,","Left":324.0,"Top":740.0,"Height":12.0,"Width":35.0},{"WordText":"already","Left":363.0,"Top":735.0,"Height":20.0,"Width":56.0}],"MaxHeight":20.0,"MinTop":735.0},{"LineText":"iamque (adv.). and now, at this point","Words":[{"WordText":"iamque","Left":239.0,"Top":762.0,"Height":17.0,"Width":58.0},{"WordText":"(adv.).","Left":301.0,"Top":761.0,"Height":17.0,"Width":46.0},{"WordText":"and","Left":352.0,"Top":762.0,"Height":14.0,"Width":28.0},{"WordText":"now,","Left":385.0,"Top":766.0,"Height":12.0,"Width":34.0},{"WordText":"at","Left":424.0,"Top":765.0,"Height":12.0,"Width":14.0},{"WordText":"this","Left":442.0,"Top":762.0,"Height":15.0,"Width":28.0},{"WordText":"point","Left":474.0,"Top":764.0,"Height":17.0,"Width":40.0}],"MaxHeight":17.0,"MinTop":761.0},{"LineText":"ib-. [see eöl","Words":[{"WordText":"ib-.","Left":239.0,"Top":788.0,"Height":14.0,"Width":26.0},{"WordText":"[see","Left":271.0,"Top":788.0,"Height":17.0,"Width":26.0},{"WordText":"eöl","Left":301.0,"Top":787.0,"Height":18.0,"Width":22.0}],"MaxHeight":18.0,"MinTop":787.0},{"LineText":"ibi (adv.). there","Words":[{"WordText":"ibi","Left":239.0,"Top":814.0,"Height":14.0,"Width":20.0},{"WordText":"(adv.).","Left":264.0,"Top":813.0,"Height":18.0,"Width":46.0},{"WordText":"there","Left":315.0,"Top":814.0,"Height":15.0,"Width":38.0}],"MaxHeight":18.0,"MinTop":813.0},{"LineText":"Icarus, -i. [name: the son of Daedalus)","Words":[{"WordText":"Icarus,","Left":240.0,"Top":838.0,"Height":18.0,"Width":53.0},{"WordText":"-i.","Left":298.0,"Top":842.0,"Height":12.0,"Width":15.0},{"WordText":"[name:","Left":319.0,"Top":840.0,"Height":17.0,"Width":49.0},{"WordText":"the","Left":374.0,"Top":840.0,"Height":15.0,"Width":22.0},{"WordText":"son","Left":399.0,"Top":846.0,"Height":10.0,"Width":25.0},{"WordText":"of","Left":429.0,"Top":841.0,"Height":19.0,"Width":17.0},{"WordText":"Daedalus)","Left":447.0,"Top":842.0,"Height":18.0,"Width":73.0}],"MaxHeight":19.0,"MinTop":838.0},{"LineText":"iciö, icere, ici, ictus. to strike, to beat","Words":[{"WordText":"iciö,","Left":239.0,"Top":867.0,"Height":15.0,"Width":33.0},{"WordText":"icere,","Left":277.0,"Top":868.0,"Height":15.0,"Width":41.0},{"WordText":"ici,","Left":322.0,"Top":868.0,"Height":15.0,"Width":23.0},{"WordText":"ictus.","Left":350.0,"Top":868.0,"Height":13.0,"Width":40.0},{"WordText":"to","Left":395.0,"Top":870.0,"Height":12.0,"Width":15.0},{"WordText":"strike,","Left":414.0,"Top":868.0,"Height":16.0,"Width":47.0},{"WordText":"to","Left":465.0,"Top":871.0,"Height":11.0,"Width":14.0},{"WordText":"beat","Left":483.0,"Top":868.0,"Height":15.0,"Width":32.0}],"MaxHeight":16.0,"MinTop":867.0},{"LineText":"ictus, -üs. a blow, a strike, a pounding","Words":[{"WordText":"ictus,","Left":240.0,"Top":893.0,"Height":16.0,"Width":41.0},{"WordText":"-üs.","Left":287.0,"Top":894.0,"Height":13.0,"Width":26.0},{"WordText":"a","Left":319.0,"Top":897.0,"Height":10.0,"Width":8.0},{"WordText":"blow,","Left":331.0,"Top":892.0,"Height":17.0,"Width":38.0},{"WordText":"a","Left":374.0,"Top":897.0,"Height":10.0,"Width":8.0},{"WordText":"strike,","Left":386.0,"Top":893.0,"Height":17.0,"Width":46.0},{"WordText":"a","Left":438.0,"Top":898.0,"Height":10.0,"Width":7.0},{"WordText":"pounding","Left":449.0,"Top":894.0,"Height":20.0,"Width":73.0}],"MaxHeight":20.0,"MinTop":892.0},{"LineText":"id. [see is, ea. idl","Words":[{"WordText":"id.","Left":240.0,"Top":918.0,"Height":15.0,"Width":19.0},{"WordText":"[see","Left":266.0,"Top":918.0,"Height":17.0,"Width":26.0},{"WordText":"is,","Left":296.0,"Top":919.0,"Height":15.0,"Width":16.0},{"WordText":"ea.","Left":316.0,"Top":923.0,"Height":12.0,"Width":21.0},{"WordText":"idl","Left":342.0,"Top":918.0,"Height":18.0,"Width":18.0}],"MaxHeight":18.0,"MinTop":918.0},{"LineText":"idem, eadem, idem. same, the same, unchanged, constant","Words":[{"WordText":"idem,","Left":239.0,"Top":945.0,"Height":16.0,"Width":44.0},{"WordText":"eadem,","Left":287.0,"Top":944.0,"Height":17.0,"Width":55.0},{"WordText":"idem.","Left":347.0,"Top":945.0,"Height":14.0,"Width":42.0},{"WordText":"same,","Left":394.0,"Top":950.0,"Height":12.0,"Width":42.0},{"WordText":"the","Left":440.0,"Top":946.0,"Height":14.0,"Width":24.0},{"WordText":"same,","Left":468.0,"Top":951.0,"Height":12.0,"Width":42.0},{"WordText":"unchanged,","Left":514.0,"Top":948.0,"Height":20.0,"Width":87.0},{"WordText":"constant","Left":605.0,"Top":954.0,"Height":13.0,"Width":65.0}],"MaxHeight":20.0,"MinTop":944.0},{"LineText":"ideo (adv.). still, therefore, for that reason","Words":[{"WordText":"ideo","Left":240.0,"Top":971.0,"Height":14.0,"Width":33.0},{"WordText":"(adv.).","Left":278.0,"Top":970.0,"Height":17.0,"Width":45.0},{"WordText":"still,","Left":328.0,"Top":970.0,"Height":17.0,"Width":32.0},{"WordText":"therefore,","Left":365.0,"Top":971.0,"Height":17.0,"Width":71.0},{"WordText":"for","Left":441.0,"Top":971.0,"Height":15.0,"Width":21.0},{"WordText":"that","Left":466.0,"Top":972.0,"Height":16.0,"Width":29.0},{"WordText":"reason","Left":499.0,"Top":978.0,"Height":11.0,"Width":49.0}],"MaxHeight":17.0,"MinTop":970.0},{"LineText":"ignärus, -a, -um. ignorant, unaware","Words":[{"WordText":"ignärus,","Left":240.0,"Top":998.0,"Height":18.0,"Width":64.0},{"WordText":"-a,","Left":309.0,"Top":1001.0,"Height":12.0,"Width":19.0},{"WordText":"-um.","Left":333.0,"Top":1000.0,"Height":11.0,"Width":36.0},{"WordText":"ignorant,","Left":373.0,"Top":997.0,"Height":18.0,"Width":68.0},{"WordText":"unaware","Left":446.0,"Top":1002.0,"Height":11.0,"Width":63.0}],"MaxHeight":18.0,"MinTop":997.0},{"LineText":"ignävus, -a, -um. cowardly, lazy","Words":[{"WordText":"ignävus,","Left":240.0,"Top":1024.0,"Height":18.0,"Width":65.0},{"WordText":"-a,","Left":310.0,"Top":1027.0,"Height":12.0,"Width":19.0},{"WordText":"-um.","Left":334.0,"Top":1027.0,"Height":9.0,"Width":35.0},{"WordText":"cowardly,","Left":374.0,"Top":1023.0,"Height":19.0,"Width":71.0},{"WordText":"lazy","Left":449.0,"Top":1023.0,"Height":19.0,"Width":31.0}],"MaxHeight":19.0,"MinTop":1023.0},{"LineText":"ignis, -is fire, flame","Words":[{"WordText":"ignis,","Left":240.0,"Top":1050.0,"Height":18.0,"Width":42.0},{"WordText":"-is","Left":288.0,"Top":1049.0,"Height":14.0,"Width":18.0},{"WordText":"fire,","Left":351.0,"Top":1048.0,"Height":16.0,"Width":28.0},{"WordText":"flame","Left":384.0,"Top":1048.0,"Height":15.0,"Width":40.0}],"MaxHeight":18.0,"MinTop":1048.0},{"LineText":"-um unfamiliar stran","Words":[{"WordText":"-um","Left":332.0,"Top":1079.0,"Height":8.0,"Width":30.0},{"WordText":"unfamiliar","Left":373.0,"Top":1074.0,"Height":15.0,"Width":80.0},{"WordText":"stran","Left":460.0,"Top":1078.0,"Height":12.0,"Width":38.0}],"MaxHeight":15.0,"MinTop":1074.0},{"LineText":"imber, imbr s m. ,","Words":[{"WordText":"imber,","Left":724.0,"Top":4.0,"Height":17.0,"Width":50.0},{"WordText":"imbr","Left":780.0,"Top":3.0,"Height":15.0,"Width":38.0},{"WordText":"s","Left":824.0,"Top":7.0,"Height":10.0,"Width":7.0},{"WordText":"m.","Left":842.0,"Top":6.0,"Height":10.0,"Width":20.0},{"WordText":",","Left":869.0,"Top":12.0,"Height":4.0,"Width":3.0}],"MaxHeight":17.0,"MinTop":3.0},{"LineText":"imitor, imitäri, imitätus, to appear as, to imitate, to","Words":[{"WordText":"imitor,","Left":723.0,"Top":33.0,"Height":15.0,"Width":54.0},{"WordText":"imitäri,","Left":782.0,"Top":31.0,"Height":15.0,"Width":61.0},{"WordText":"imitätus,","Left":848.0,"Top":29.0,"Height":14.0,"Width":72.0},{"WordText":"to","Left":925.0,"Top":29.0,"Height":12.0,"Width":15.0},{"WordText":"appear","Left":946.0,"Top":30.0,"Height":15.0,"Width":53.0},{"WordText":"as,","Left":1004.0,"Top":30.0,"Height":12.0,"Width":20.0},{"WordText":"to","Left":1029.0,"Top":28.0,"Height":13.0,"Width":15.0},{"WordText":"imitate,","Left":1049.0,"Top":27.0,"Height":17.0,"Width":59.0},{"WordText":"to","Left":1113.0,"Top":31.0,"Height":13.0,"Width":14.0}],"MaxHeight":17.0,"MinTop":27.0},{"LineText":"resemble","Words":[{"WordText":"resemble","Left":761.0,"Top":52.0,"Height":17.0,"Width":69.0}],"MaxHeight":17.0,"MinTop":52.0},{"LineText":"immensus, -a, -um. immense, huge","Words":[{"WordText":"immensus,","Left":723.0,"Top":83.0,"Height":14.0,"Width":86.0},{"WordText":"-a,","Left":814.0,"Top":84.0,"Height":12.0,"Width":20.0},{"WordText":"-um.","Left":839.0,"Top":83.0,"Height":11.0,"Width":37.0},{"WordText":"immense,","Left":882.0,"Top":79.0,"Height":14.0,"Width":76.0},{"WordText":"huge","Left":963.0,"Top":76.0,"Height":20.0,"Width":38.0}],"MaxHeight":20.0,"MinTop":76.0},{"LineText":"immineö, imminére, - (+ dat.). to hang over, to threaten,","Words":[{"WordText":"immineö,","Left":723.0,"Top":109.0,"Height":16.0,"Width":77.0},{"WordText":"imminére,","Left":804.0,"Top":107.0,"Height":15.0,"Width":84.0},{"WordText":"-","Left":909.0,"Top":113.0,"Height":3.0,"Width":6.0},{"WordText":"(+","Left":920.0,"Top":105.0,"Height":17.0,"Width":15.0},{"WordText":"dat.).","Left":941.0,"Top":104.0,"Height":17.0,"Width":40.0},{"WordText":"to","Left":987.0,"Top":107.0,"Height":12.0,"Width":15.0},{"WordText":"hang","Left":1007.0,"Top":104.0,"Height":20.0,"Width":39.0},{"WordText":"over,","Left":1050.0,"Top":109.0,"Height":13.0,"Width":37.0},{"WordText":"to","Left":1092.0,"Top":108.0,"Height":13.0,"Width":14.0},{"WordText":"threaten,","Left":1111.0,"Top":107.0,"Height":21.0,"Width":65.0}],"MaxHeight":21.0,"MinTop":104.0},{"LineText":"to press upon","Words":[{"WordText":"to","Left":760.0,"Top":134.0,"Height":13.0,"Width":15.0},{"WordText":"press","Left":780.0,"Top":135.0,"Height":15.0,"Width":39.0},{"WordText":"upon","Left":824.0,"Top":134.0,"Height":15.0,"Width":40.0}],"MaxHeight":15.0,"MinTop":134.0},{"LineText":"immundus, -a, -urn. unclean, sordid, dirty","Words":[{"WordText":"immundus,","Left":723.0,"Top":159.0,"Height":16.0,"Width":90.0},{"WordText":"-a,","Left":819.0,"Top":162.0,"Height":12.0,"Width":19.0},{"WordText":"-urn.","Left":843.0,"Top":161.0,"Height":11.0,"Width":38.0},{"WordText":"unclean,","Left":886.0,"Top":156.0,"Height":16.0,"Width":67.0},{"WordText":"sordid,","Left":958.0,"Top":155.0,"Height":17.0,"Width":54.0},{"WordText":"dirty","Left":1017.0,"Top":155.0,"Height":20.0,"Width":40.0}],"MaxHeight":20.0,"MinTop":155.0},{"LineText":"immünis, -e. immune, free (from), free (of), exempt (from)","Words":[{"WordText":"immünis,","Left":722.0,"Top":187.0,"Height":16.0,"Width":76.0},{"WordText":"-e.","Left":804.0,"Top":190.0,"Height":11.0,"Width":18.0},{"WordText":"immune,","Left":828.0,"Top":186.0,"Height":15.0,"Width":70.0},{"WordText":"free","Left":904.0,"Top":183.0,"Height":15.0,"Width":29.0},{"WordText":"(from),","Left":939.0,"Top":183.0,"Height":18.0,"Width":54.0},{"WordText":"free","Left":998.0,"Top":182.0,"Height":16.0,"Width":30.0},{"WordText":"(of),","Left":1033.0,"Top":183.0,"Height":18.0,"Width":32.0},{"WordText":"exempt","Left":1070.0,"Top":188.0,"Height":17.0,"Width":55.0},{"WordText":"(from)","Left":1130.0,"Top":186.0,"Height":20.0,"Width":44.0}],"MaxHeight":20.0,"MinTop":182.0},{"LineText":"impär, imparis. unequal, uneven","Words":[{"WordText":"impär,","Left":722.0,"Top":215.0,"Height":18.0,"Width":51.0},{"WordText":"imparis.","Left":778.0,"Top":214.0,"Height":19.0,"Width":66.0},{"WordText":"unequal,","Left":849.0,"Top":211.0,"Height":20.0,"Width":68.0},{"WordText":"uneven","Left":923.0,"Top":215.0,"Height":11.0,"Width":57.0}],"MaxHeight":20.0,"MinTop":211.0},{"LineText":"impatiens, impatientis (+ gen.). impatient, intolerant (of)","Words":[{"WordText":"impatiens,","Left":722.0,"Top":243.0,"Height":18.0,"Width":82.0},{"WordText":"impatientis","Left":809.0,"Top":241.0,"Height":19.0,"Width":90.0},{"WordText":"(+","Left":905.0,"Top":239.0,"Height":18.0,"Width":15.0},{"WordText":"gen.).","Left":925.0,"Top":239.0,"Height":20.0,"Width":43.0},{"WordText":"impatient,","Left":974.0,"Top":240.0,"Height":18.0,"Width":80.0},{"WordText":"intolerant","Left":1059.0,"Top":239.0,"Height":17.0,"Width":75.0},{"WordText":"(of)","Left":1138.0,"Top":242.0,"Height":19.0,"Width":25.0}],"MaxHeight":20.0,"MinTop":239.0},{"LineText":"impediö, impedire, impedivi, impeditus. to hinder, to get","Words":[{"WordText":"impediö,","Left":722.0,"Top":269.0,"Height":19.0,"Width":69.0},{"WordText":"impedire,","Left":796.0,"Top":268.0,"Height":20.0,"Width":77.0},{"WordText":"impedivi,","Left":878.0,"Top":267.0,"Height":19.0,"Width":78.0},{"WordText":"impeditus.","Left":961.0,"Top":267.0,"Height":18.0,"Width":86.0},{"WordText":"to","Left":1053.0,"Top":269.0,"Height":13.0,"Width":15.0},{"WordText":"hinder,","Left":1072.0,"Top":267.0,"Height":18.0,"Width":54.0},{"WordText":"to","Left":1131.0,"Top":272.0,"Height":12.0,"Width":13.0},{"WordText":"get","Left":1149.0,"Top":274.0,"Height":15.0,"Width":21.0}],"MaxHeight":20.0,"MinTop":267.0},{"LineText":"in the way of, to impede","Words":[{"WordText":"in","Left":759.0,"Top":294.0,"Height":13.0,"Width":15.0},{"WordText":"the","Left":779.0,"Top":292.0,"Height":15.0,"Width":24.0},{"WordText":"way","Left":807.0,"Top":297.0,"Height":14.0,"Width":31.0},{"WordText":"of,","Left":842.0,"Top":291.0,"Height":17.0,"Width":19.0},{"WordText":"to","Left":866.0,"Top":294.0,"Height":12.0,"Width":15.0},{"WordText":"impede","Left":886.0,"Top":290.0,"Height":20.0,"Width":58.0}],"MaxHeight":20.0,"MinTop":290.0},{"LineText":"impellö, impeller, impuli, impulsus. to strike against, to","Words":[{"WordText":"impellö,","Left":721.0,"Top":320.0,"Height":19.0,"Width":64.0},{"WordText":"impeller,","Left":790.0,"Top":319.0,"Height":20.0,"Width":79.0},{"WordText":"impuli,","Left":874.0,"Top":318.0,"Height":19.0,"Width":59.0},{"WordText":"impulsus.","Left":937.0,"Top":317.0,"Height":20.0,"Width":79.0},{"WordText":"to","Left":1022.0,"Top":320.0,"Height":12.0,"Width":15.0},{"WordText":"strike","Left":1041.0,"Top":318.0,"Height":15.0,"Width":45.0},{"WordText":"against,","Left":1090.0,"Top":320.0,"Height":18.0,"Width":57.0},{"WordText":"to","Left":1152.0,"Top":323.0,"Height":13.0,"Width":14.0}],"MaxHeight":20.0,"MinTop":317.0},{"LineText":"beat, to compel","Words":[{"WordText":"beat,","Left":758.0,"Top":343.0,"Height":17.0,"Width":36.0},{"WordText":"to","Left":799.0,"Top":345.0,"Height":12.0,"Width":15.0},{"WordText":"compel","Left":818.0,"Top":342.0,"Height":19.0,"Width":56.0}],"MaxHeight":19.0,"MinTop":342.0},{"LineText":"imperfectus, -a, -um. incomplete, unfinished","Words":[{"WordText":"imperfectus,","Left":721.0,"Top":370.0,"Height":19.0,"Width":98.0},{"WordText":"-a,","Left":824.0,"Top":374.0,"Height":13.0,"Width":19.0},{"WordText":"-um.","Left":848.0,"Top":374.0,"Height":10.0,"Width":38.0},{"WordText":"incomplete,","Left":891.0,"Top":369.0,"Height":19.0,"Width":92.0},{"WordText":"unfinished","Left":988.0,"Top":368.0,"Height":15.0,"Width":84.0}],"MaxHeight":19.0,"MinTop":368.0},{"LineText":"impiger, impigra, impigrum. swift, quick, fast","Words":[{"WordText":"impiger,","Left":720.0,"Top":398.0,"Height":18.0,"Width":64.0},{"WordText":"impigra,","Left":789.0,"Top":398.0,"Height":18.0,"Width":67.0},{"WordText":"impigrum.","Left":861.0,"Top":398.0,"Height":18.0,"Width":86.0},{"WordText":"swift,","Left":953.0,"Top":396.0,"Height":17.0,"Width":43.0},{"WordText":"quick,","Left":1001.0,"Top":396.0,"Height":19.0,"Width":48.0},{"WordText":"fast","Left":1054.0,"Top":396.0,"Height":15.0,"Width":27.0}],"MaxHeight":19.0,"MinTop":396.0},{"LineText":"impius, -a, -urn. disloyal, impious, lacking religious","Words":[{"WordText":"impius,","Left":720.0,"Top":425.0,"Height":18.0,"Width":58.0},{"WordText":"-a,","Left":783.0,"Top":429.0,"Height":12.0,"Width":19.0},{"WordText":"-urn.","Left":808.0,"Top":429.0,"Height":10.0,"Width":36.0},{"WordText":"disloyal,","Left":849.0,"Top":424.0,"Height":19.0,"Width":64.0},{"WordText":"impious,","Left":918.0,"Top":425.0,"Height":18.0,"Width":68.0},{"WordText":"lacking","Left":992.0,"Top":424.0,"Height":20.0,"Width":58.0},{"WordText":"religious","Left":1054.0,"Top":424.0,"Height":20.0,"Width":66.0}],"MaxHeight":20.0,"MinTop":424.0},{"LineText":"devotion","Words":[{"WordText":"devotion","Left":757.0,"Top":447.0,"Height":15.0,"Width":67.0}],"MaxHeight":15.0,"MinTop":447.0},{"LineText":"impleö, implere, implévi, implétus. to fill, to fill up","Words":[{"WordText":"impleö,","Left":720.0,"Top":474.0,"Height":18.0,"Width":58.0},{"WordText":"implere,","Left":783.0,"Top":474.0,"Height":19.0,"Width":64.0},{"WordText":"implévi,","Left":852.0,"Top":475.0,"Height":18.0,"Width":64.0},{"WordText":"implétus.","Left":922.0,"Top":474.0,"Height":19.0,"Width":75.0},{"WordText":"to","Left":1002.0,"Top":477.0,"Height":12.0,"Width":16.0},{"WordText":"fill,","Left":1023.0,"Top":474.0,"Height":17.0,"Width":25.0},{"WordText":"to","Left":1053.0,"Top":477.0,"Height":13.0,"Width":15.0},{"WordText":"fill","Left":1072.0,"Top":474.0,"Height":16.0,"Width":21.0},{"WordText":"up","Left":1098.0,"Top":480.0,"Height":15.0,"Width":19.0}],"MaxHeight":19.0,"MinTop":474.0},{"LineText":"impönö, impönere, imposui, impositus. to put on, to","Words":[{"WordText":"impönö,","Left":719.0,"Top":501.0,"Height":18.0,"Width":65.0},{"WordText":"impönere,","Left":789.0,"Top":502.0,"Height":18.0,"Width":80.0},{"WordText":"imposui,","Left":874.0,"Top":502.0,"Height":18.0,"Width":70.0},{"WordText":"impositus.","Left":949.0,"Top":503.0,"Height":18.0,"Width":85.0},{"WordText":"to","Left":1039.0,"Top":505.0,"Height":12.0,"Width":16.0},{"WordText":"put","Left":1059.0,"Top":505.0,"Height":16.0,"Width":26.0},{"WordText":"on,","Left":1089.0,"Top":508.0,"Height":11.0,"Width":24.0},{"WordText":"to","Left":1117.0,"Top":506.0,"Height":12.0,"Width":15.0}],"MaxHeight":18.0,"MinTop":501.0},{"LineText":"place on, to cover","Words":[{"WordText":"place","Left":756.0,"Top":523.0,"Height":19.0,"Width":39.0},{"WordText":"on,","Left":799.0,"Top":528.0,"Height":12.0,"Width":24.0},{"WordText":"to","Left":827.0,"Top":526.0,"Height":12.0,"Width":15.0},{"WordText":"cover","Left":847.0,"Top":529.0,"Height":10.0,"Width":42.0}],"MaxHeight":19.0,"MinTop":523.0},{"LineText":"imus, -a, -urn. the lowest (part of)","Words":[{"WordText":"imus,","Left":719.0,"Top":550.0,"Height":16.0,"Width":43.0},{"WordText":"-a,","Left":767.0,"Top":554.0,"Height":13.0,"Width":19.0},{"WordText":"-urn.","Left":790.0,"Top":555.0,"Height":10.0,"Width":37.0},{"WordText":"the","Left":832.0,"Top":550.0,"Height":15.0,"Width":24.0},{"WordText":"lowest","Left":861.0,"Top":551.0,"Height":15.0,"Width":48.0},{"WordText":"(part","Left":914.0,"Top":552.0,"Height":18.0,"Width":39.0},{"WordText":"of)","Left":957.0,"Top":552.0,"Height":18.0,"Width":23.0}],"MaxHeight":18.0,"MinTop":550.0},{"LineText":"in (prep. w/ acc.). into, onto","Words":[{"WordText":"in","Left":719.0,"Top":577.0,"Height":13.0,"Width":16.0},{"WordText":"(prep.","Left":739.0,"Top":576.0,"Height":19.0,"Width":45.0},{"WordText":"w/","Left":788.0,"Top":577.0,"Height":15.0,"Width":19.0},{"WordText":"acc.).","Left":811.0,"Top":577.0,"Height":18.0,"Width":39.0},{"WordText":"into,","Left":856.0,"Top":579.0,"Height":15.0,"Width":35.0},{"WordText":"onto","Left":895.0,"Top":581.0,"Height":12.0,"Width":35.0}],"MaxHeight":19.0,"MinTop":576.0},{"LineText":"in (prep. w/ abl.). in, on","Words":[{"WordText":"in","Left":718.0,"Top":603.0,"Height":14.0,"Width":16.0},{"WordText":"(prep.","Left":739.0,"Top":603.0,"Height":18.0,"Width":44.0},{"WordText":"w/","Left":788.0,"Top":604.0,"Height":15.0,"Width":18.0},{"WordText":"abl.).","Left":811.0,"Top":604.0,"Height":17.0,"Width":38.0},{"WordText":"in,","Left":854.0,"Top":606.0,"Height":15.0,"Width":19.0},{"WordText":"on","Left":878.0,"Top":610.0,"Height":10.0,"Width":20.0}],"MaxHeight":18.0,"MinTop":603.0},{"LineText":"incertus, -a, -urn. uncertain","Words":[{"WordText":"incertus,","Left":719.0,"Top":630.0,"Height":17.0,"Width":67.0},{"WordText":"-a,","Left":791.0,"Top":635.0,"Height":12.0,"Width":19.0},{"WordText":"-urn.","Left":815.0,"Top":636.0,"Height":10.0,"Width":36.0},{"WordText":"uncertain","Left":857.0,"Top":634.0,"Height":14.0,"Width":76.0}],"MaxHeight":17.0,"MinTop":630.0},{"LineText":"incola, -ae inhabitant, resident","Words":[{"WordText":"incola,","Left":718.0,"Top":656.0,"Height":17.0,"Width":51.0},{"WordText":"-ae","Left":774.0,"Top":661.0,"Height":10.0,"Width":24.0},{"WordText":"inhabitant,","Left":843.0,"Top":659.0,"Height":18.0,"Width":85.0},{"WordText":"resident","Left":933.0,"Top":661.0,"Height":15.0,"Width":63.0}],"MaxHeight":18.0,"MinTop":656.0},{"LineText":"increpö, increpäre, increpui, increpitus. to beat loudly, to","Words":[{"WordText":"increpö,","Left":718.0,"Top":683.0,"Height":18.0,"Width":63.0},{"WordText":"increpäre,","Left":786.0,"Top":685.0,"Height":18.0,"Width":79.0},{"WordText":"increpui,","Left":870.0,"Top":687.0,"Height":19.0,"Width":71.0},{"WordText":"increpitus.","Left":947.0,"Top":689.0,"Height":19.0,"Width":85.0},{"WordText":"to","Left":1037.0,"Top":692.0,"Height":13.0,"Width":16.0},{"WordText":"beat","Left":1057.0,"Top":690.0,"Height":15.0,"Width":33.0},{"WordText":"loudly,","Left":1093.0,"Top":690.0,"Height":19.0,"Width":49.0},{"WordText":"to","Left":1146.0,"Top":692.0,"Height":12.0,"Width":15.0}],"MaxHeight":19.0,"MinTop":683.0},{"LineText":"strike loudly, to make noise, to make a loud noise","Words":[{"WordText":"strike","Left":754.0,"Top":706.0,"Height":14.0,"Width":43.0},{"WordText":"loudly,","Left":802.0,"Top":706.0,"Height":20.0,"Width":52.0},{"WordText":"to","Left":860.0,"Top":711.0,"Height":12.0,"Width":14.0},{"WordText":"make","Left":879.0,"Top":710.0,"Height":15.0,"Width":42.0},{"WordText":"noise,","Left":926.0,"Top":712.0,"Height":16.0,"Width":46.0},{"WordText":"to","Left":977.0,"Top":714.0,"Height":13.0,"Width":15.0},{"WordText":"make","Left":996.0,"Top":713.0,"Height":14.0,"Width":43.0},{"WordText":"a","Left":1044.0,"Top":718.0,"Height":10.0,"Width":8.0},{"WordText":"loud","Left":1056.0,"Top":713.0,"Height":15.0,"Width":34.0},{"WordText":"noise","Left":1095.0,"Top":714.0,"Height":14.0,"Width":38.0}],"MaxHeight":20.0,"MinTop":706.0},{"LineText":"incumbö, incumbere, incubui, - (+ dat.). to fall (on), to lie","Words":[{"WordText":"incumbö,","Left":717.0,"Top":732.0,"Height":17.0,"Width":74.0},{"WordText":"incumbere,","Left":796.0,"Top":734.0,"Height":19.0,"Width":89.0},{"WordText":"incubui,","Left":890.0,"Top":737.0,"Height":18.0,"Width":66.0},{"WordText":"-","Left":961.0,"Top":747.0,"Height":2.0,"Width":6.0},{"WordText":"(+","Left":972.0,"Top":739.0,"Height":17.0,"Width":16.0},{"WordText":"dat.).","Left":993.0,"Top":739.0,"Height":19.0,"Width":40.0},{"WordText":"to","Left":1039.0,"Top":743.0,"Height":12.0,"Width":15.0},{"WordText":"fall","Left":1058.0,"Top":740.0,"Height":15.0,"Width":25.0},{"WordText":"(on),","Left":1088.0,"Top":740.0,"Height":18.0,"Width":33.0},{"WordText":"to","Left":1125.0,"Top":743.0,"Height":12.0,"Width":15.0},{"WordText":"lie","Left":1143.0,"Top":739.0,"Height":15.0,"Width":17.0}],"MaxHeight":19.0,"MinTop":732.0},{"LineText":"down (on), to thrust oneself (on)","Words":[{"WordText":"down","Left":754.0,"Top":754.0,"Height":16.0,"Width":43.0},{"WordText":"(on),","Left":802.0,"Top":756.0,"Height":18.0,"Width":33.0},{"WordText":"to","Left":841.0,"Top":760.0,"Height":12.0,"Width":14.0},{"WordText":"thrust","Left":860.0,"Top":758.0,"Height":16.0,"Width":48.0},{"WordText":"oneself","Left":912.0,"Top":761.0,"Height":15.0,"Width":58.0},{"WordText":"(on)","Left":973.0,"Top":762.0,"Height":18.0,"Width":30.0}],"MaxHeight":18.0,"MinTop":754.0},{"LineText":"inde (adv.). from there, next","Words":[{"WordText":"inde","Left":717.0,"Top":781.0,"Height":14.0,"Width":33.0},{"WordText":"(adv.).","Left":756.0,"Top":781.0,"Height":18.0,"Width":45.0},{"WordText":"from","Left":806.0,"Top":783.0,"Height":16.0,"Width":38.0},{"WordText":"there,","Left":849.0,"Top":785.0,"Height":18.0,"Width":43.0},{"WordText":"next","Left":897.0,"Top":790.0,"Height":13.0,"Width":34.0}],"MaxHeight":18.0,"MinTop":781.0},{"LineText":"indignor, indignäri, indignätus. to view as inappropriate,","Words":[{"WordText":"indignor,","Left":716.0,"Top":808.0,"Height":19.0,"Width":72.0},{"WordText":"indignäri,","Left":793.0,"Top":811.0,"Height":19.0,"Width":79.0},{"WordText":"indignätus.","Left":877.0,"Top":814.0,"Height":20.0,"Width":91.0},{"WordText":"to","Left":973.0,"Top":819.0,"Height":13.0,"Width":15.0},{"WordText":"view","Left":993.0,"Top":818.0,"Height":14.0,"Width":37.0},{"WordText":"as","Left":1034.0,"Top":822.0,"Height":10.0,"Width":15.0},{"WordText":"inappropriate,","Left":1054.0,"Top":817.0,"Height":20.0,"Width":104.0}],"MaxHeight":20.0,"MinTop":808.0},{"LineText":"to view as unworthy","Words":[{"WordText":"to","Left":753.0,"Top":833.0,"Height":12.0,"Width":15.0},{"WordText":"view","Left":772.0,"Top":833.0,"Height":14.0,"Width":36.0},{"WordText":"as","Left":812.0,"Top":838.0,"Height":10.0,"Width":15.0},{"WordText":"unworthy","Left":832.0,"Top":836.0,"Height":20.0,"Width":76.0}],"MaxHeight":20.0,"MinTop":833.0},{"LineText":"indignus, -a, -um (+ abl.). unworthy, undeserving","Words":[{"WordText":"indignus,","Left":716.0,"Top":857.0,"Height":19.0,"Width":73.0},{"WordText":"-a,","Left":794.0,"Top":864.0,"Height":12.0,"Width":20.0},{"WordText":"-um","Left":818.0,"Top":865.0,"Height":11.0,"Width":33.0},{"WordText":"(+","Left":856.0,"Top":862.0,"Height":18.0,"Width":15.0},{"WordText":"abl.).","Left":876.0,"Top":863.0,"Height":19.0,"Width":39.0},{"WordText":"unworthy,","Left":920.0,"Top":867.0,"Height":19.0,"Width":80.0},{"WordText":"undeserving","Left":1005.0,"Top":867.0,"Height":19.0,"Width":95.0}],"MaxHeight":19.0,"MinTop":857.0},{"LineText":"indücö, indücere, induxi, inductus. to lead up, to lead in,","Words":[{"WordText":"indücö,","Left":716.0,"Top":884.0,"Height":18.0,"Width":58.0},{"WordText":"indücere,","Left":779.0,"Top":887.0,"Height":18.0,"Width":72.0},{"WordText":"induxi,","Left":856.0,"Top":890.0,"Height":18.0,"Width":58.0},{"WordText":"inductus.","Left":918.0,"Top":893.0,"Height":16.0,"Width":75.0},{"WordText":"to","Left":997.0,"Top":897.0,"Height":13.0,"Width":16.0},{"WordText":"lead","Left":1017.0,"Top":894.0,"Height":16.0,"Width":32.0},{"WordText":"up,","Left":1053.0,"Top":899.0,"Height":14.0,"Width":24.0},{"WordText":"to","Left":1081.0,"Top":897.0,"Height":12.0,"Width":15.0},{"WordText":"lead","Left":1100.0,"Top":893.0,"Height":15.0,"Width":30.0},{"WordText":"in,","Left":1134.0,"Top":893.0,"Height":15.0,"Width":18.0}],"MaxHeight":18.0,"MinTop":884.0},{"LineText":"to lead into; to cover","Words":[{"WordText":"to","Left":753.0,"Top":910.0,"Height":12.0,"Width":14.0},{"WordText":"lead","Left":772.0,"Top":908.0,"Height":16.0,"Width":31.0},{"WordText":"into;","Left":808.0,"Top":910.0,"Height":17.0,"Width":34.0},{"WordText":"to","Left":847.0,"Top":914.0,"Height":12.0,"Width":15.0},{"WordText":"cover","Left":867.0,"Top":917.0,"Height":11.0,"Width":42.0}],"MaxHeight":17.0,"MinTop":908.0},{"LineText":"indürescö, indürescere, indürui, to harden, to grow","Words":[{"WordText":"indürescö,","Left":716.0,"Top":933.0,"Height":19.0,"Width":81.0},{"WordText":"indürescere,","Left":802.0,"Top":937.0,"Height":20.0,"Width":96.0},{"WordText":"indürui,","Left":903.0,"Top":942.0,"Height":18.0,"Width":67.0},{"WordText":"to","Left":990.0,"Top":946.0,"Height":12.0,"Width":15.0},{"WordText":"harden,","Left":1010.0,"Top":944.0,"Height":16.0,"Width":58.0},{"WordText":"to","Left":1073.0,"Top":947.0,"Height":11.0,"Width":13.0},{"WordText":"grow","Left":1091.0,"Top":946.0,"Height":16.0,"Width":37.0}],"MaxHeight":20.0,"MinTop":933.0},{"LineText":"hard, to stiffen","Words":[{"WordText":"hard,","Left":752.0,"Top":956.0,"Height":18.0,"Width":39.0},{"WordText":"to","Left":796.0,"Top":961.0,"Height":12.0,"Width":15.0},{"WordText":"stiffen","Left":816.0,"Top":961.0,"Height":15.0,"Width":47.0}],"MaxHeight":18.0,"MinTop":956.0},{"LineText":"inermis, -e. unharmed","Words":[{"WordText":"inermis,","Left":715.0,"Top":982.0,"Height":19.0,"Width":64.0},{"WordText":"-e.","Left":784.0,"Top":989.0,"Height":11.0,"Width":19.0},{"WordText":"unharmed","Left":807.0,"Top":987.0,"Height":17.0,"Width":82.0}],"MaxHeight":19.0,"MinTop":982.0},{"LineText":"iners, inertis. lazy, slow, lifeless","Words":[{"WordText":"iners,","Left":714.0,"Top":1008.0,"Height":17.0,"Width":43.0},{"WordText":"inertis.","Left":762.0,"Top":1011.0,"Height":16.0,"Width":55.0},{"WordText":"lazy,","Left":822.0,"Top":1013.0,"Height":20.0,"Width":34.0},{"WordText":"slow,","Left":861.0,"Top":1015.0,"Height":18.0,"Width":37.0},{"WordText":"lifeless","Left":902.0,"Top":1017.0,"Height":17.0,"Width":52.0}],"MaxHeight":20.0,"MinTop":1008.0},{"LineText":"infämis, -e. infamous, notorious, of ill repute","Words":[{"WordText":"infämis,","Left":714.0,"Top":1034.0,"Height":19.0,"Width":65.0},{"WordText":"-e.","Left":784.0,"Top":1042.0,"Height":10.0,"Width":18.0},{"WordText":"infamous,","Left":807.0,"Top":1039.0,"Height":20.0,"Width":78.0},{"WordText":"notorious,","Left":890.0,"Top":1046.0,"Height":17.0,"Width":78.0},{"WordText":"of","Left":973.0,"Top":1046.0,"Height":15.0,"Width":17.0},{"WordText":"ill","Left":993.0,"Top":1047.0,"Height":15.0,"Width":15.0},{"WordText":"repute","Left":1014.0,"Top":1050.0,"Height":16.0,"Width":47.0}],"MaxHeight":20.0,"MinTop":1034.0},{"LineText":"infélix, infelicis. unhappy, unfortunate, unlucky","Words":[{"WordText":"infélix,","Left":715.0,"Top":1060.0,"Height":19.0,"Width":54.0},{"WordText":"infelicis.","Left":774.0,"Top":1064.0,"Height":17.0,"Width":66.0},{"WordText":"unhappy,","Left":845.0,"Top":1068.0,"Height":21.0,"Width":71.0},{"WordText":"unfortunate,","Left":921.0,"Top":1072.0,"Height":18.0,"Width":98.0},{"WordText":"unlucky","Left":1023.0,"Top":1074.0,"Height":18.0,"Width":63.0}],"MaxHeight":21.0,"MinTop":1060.0}],"HasOverlay":true,"Message":"Total lines: 83"},"TextOrientation":"0","FileParseExitCode":1,"ParsedText":"héres, herédis (m.). heir\r\nhérös, heroidis hero\r\nhesternus, -a, -um. of or belonging to yesterday,\r\nyesterday's\r\nheu (interj.). alas! Oh no!\r\nhic, haec, hoc. this\r\nhinc (adv.). from here, next; [with illincl on this side\r\nhisco, hiscere, -, to open, to yawn\r\nhodié (adv.). today\r\nholus, holeris vegetable\r\nhonestus, -a, -urn. honorable, forthright, upstanding\r\nhonor, honoris honor, glory, distinction, beauty\r\nhöra, -ae. hour, time\r\nhorridus, -a, -urn. horrid, horrible, awful, terrible\r\nhortor, hortäri, hortätus. to encourage\r\nhortus, -i. garden\r\nhospes, hospitis (m.). guest, host, friend, visitor\r\nhostis, -is enemy\r\nhüc (adv.). to this place, here\r\nhumilis, -e. humble, lowly\r\nhumus, -i (f.). earth, dirt, soil\r\nHymén, Hymenis (name: god of marriage]\r\nHymettius, -a, -urn. Hymettian; of or belonging to Mt.\r\nHymettius [a mountain near Athens noted for its\r\nhoney]\r\niaceö, iacére, iacui, iaciturus. to lie down, to lie still, to lie\r\nmotionless\r\niam (adv.). now, already\r\niamque (adv.). and now, at this point\r\nib-. [see eöl\r\nibi (adv.). there\r\nIcarus, -i. [name: the son of Daedalus)\r\niciö, icere, ici, ictus. to strike, to beat\r\nictus, -üs. a blow, a strike, a pounding\r\nid. [see is, ea. idl\r\nidem, eadem, idem. same, the same, unchanged, constant\r\nideo (adv.). still, therefore, for that reason\r\nignärus, -a, -um. ignorant, unaware\r\nignävus, -a, -um. cowardly, lazy\r\nignis, -is fire, flame\r\n-um unfamiliar stran\r\nimber, imbr s m. ,\r\nimitor, imitäri, imitätus, to appear as, to imitate, to\r\nresemble\r\nimmensus, -a, -um. immense, huge\r\nimmineö, imminére, - (+ dat.). to hang over, to threaten,\r\nto press upon\r\nimmundus, -a, -urn. unclean, sordid, dirty\r\nimmünis, -e. immune, free (from), free (of), exempt (from)\r\nimpär, imparis. unequal, uneven\r\nimpatiens, impatientis (+ gen.). impatient, intolerant (of)\r\nimpediö, impedire, impedivi, impeditus. to hinder, to get\r\nin the way of, to impede\r\nimpellö, impeller, impuli, impulsus. to strike against, to\r\nbeat, to compel\r\nimperfectus, -a, -um. incomplete, unfinished\r\nimpiger, impigra, impigrum. swift, quick, fast\r\nimpius, -a, -urn. disloyal, impious, lacking religious\r\ndevotion\r\nimpleö, implere, implévi, implétus. to fill, to fill up\r\nimpönö, impönere, imposui, impositus. to put on, to\r\nplace on, to cover\r\nimus, -a, -urn. the lowest (part of)\r\nin (prep. w/ acc.). into, onto\r\nin (prep. w/ abl.). in, on\r\nincertus, -a, -urn. uncertain\r\nincola, -ae inhabitant, resident\r\nincrepö, increpäre, increpui, increpitus. to beat loudly, to\r\nstrike loudly, to make noise, to make a loud noise\r\nincumbö, incumbere, incubui, - (+ dat.). to fall (on), to lie\r\ndown (on), to thrust oneself (on)\r\ninde (adv.). from there, next\r\nindignor, indignäri, indignätus. to view as inappropriate,\r\nto view as unworthy\r\nindignus, -a, -um (+ abl.). unworthy, undeserving\r\nindücö, indücere, induxi, inductus. to lead up, to lead in,\r\nto lead into; to cover\r\nindürescö, indürescere, indürui, to harden, to grow\r\nhard, to stiffen\r\ninermis, -e. unharmed\r\niners, inertis. lazy, slow, lifeless\r\ninfämis, -e. infamous, notorious, of ill repute\r\ninfélix, infelicis. unhappy, unfortunate, unlucky\r\n","ErrorMessage":"","ErrorDetails":""}],"OCRExitCode":1,"IsErroredOnProcessing":false,"ProcessingTimeInMilliseconds":"1413","SearchablePDFURL":"Searchable PDF not generated as it was not requested."}